KOMPOTpy/KOMPOTpy.py
KOMPOTpy/__init__.py
kompotpy-0.0.1.dist-info/METADATA
kompotpy-0.0.1.dist-info/WHEEL
kompotpy-0.0.1.dist-info/top_level.txt
kompotpy-0.0.1.dist-info/RECORD
