Metadata-Version: 2.4
Name: KOMPOTpy
Version: 0.0.1
Summary: A package that should make the analysis of KOMPOT tables easier for my Master's thesis.
Author-email: Paul Frühwirth <paul.m.fruehwirth@gmail.com>
License-Expression: MIT
Project-URL: Homepage, https://github.com/Alfred-Gitchcock/KOMPOTpy
Project-URL: Issues, https://github.com/Alfred-Gitchcock/KOMPOTpy/issues
Classifier: Programming Language :: Python :: 3
Classifier: Operating System :: OS Independent
Requires-Python: >=3.9
